Metadata-Version: 2.1
Name: datadog-serverless-utils
Version: 1.0.7
Summary: Utilities for integration between serverless execution environments and DataDog
Home-page: https://github.com/newtonx-inc/datadog-serverless-utils
Author: NewtonX
Author-email: 
License: UNKNOWN
Platform: UNKNOWN
Requires-Python: >=3.4
License-File: LICENSE
